bidongorx/__init__.py
bidongorx/proverbes/__init__.py
bidongorx/proverbes/tellme.py
bidongorx-0.1.0.dist-info/LICENSE
bidongorx-0.1.0.dist-info/METADATA
bidongorx-0.1.0.dist-info/WHEEL
bidongorx-0.1.0.dist-info/top_level.txt
bidongorx-0.1.0.dist-info/RECORD
